pyrelatics/__init__.py
pyrelatics/client.py
pyrelatics/typings.py
pyrelatics/utils.py
pyrelatics-0.21.dist-info/DESCRIPTION.rst
pyrelatics-0.21.dist-info/METADATA
pyrelatics-0.21.dist-info/RECORD
pyrelatics-0.21.dist-info/WHEEL
pyrelatics-0.21.dist-info/metadata.json
pyrelatics-0.21.dist-info/top_level.txt
