Metadata-Version: 2.0
Name: pyrelatics
Version: 0.21
Summary: API for Relatics connections
Home-page: https://github.com/IMAMBAKS/pyrelatics
Author: Rashied Imambaks
Author-email: r@imambaks.nl
License: MIT
Keywords: relatics,SOAP,API,DB
Platform: UNKNOWN
Classifier: Development Status :: 5 - Production/Stable
Classifier: Intended Audience :: Developers
Classifier: Natural Language :: English
Classifier: License :: OSI Approved :: MIT License
Classifier: Operating System :: OS Independent
Classifier: Programming Language :: Python
Classifier: Programming Language :: Python :: 3
Classifier: Programming Language :: Python :: 3.3
Classifier: Programming Language :: Python :: 3.5
Classifier: Topic :: Software Development :: Libraries :: Python Modules
Requires-Dist: beautifulsoup4 (>=4)
Requires-Dist: suds-jurko (==0.6)
